[
  {
    "step": "fetch_data",
    "status": "success",
    "timestamp": "2026-06-06T23:37:41",
    "rows": 200
  },
  {
    "step": "preprocess_data",
    "status": "success",
    "timestamp": "2026-06-06T23:37:41",
    "features": [
      "tenure",
      "monthly_charges",
      "num_products",
      "has_internet",
      "support_calls",
      "contract_months"
    ]
  },
  {
    "step": "train_model",
    "status": "success",
    "timestamp": "2026-06-06T23:37:41",
    "metrics": {
      "accuracy": 0.75,
      "f1": 0.0,
      "roc_auc": 0.4883
    }
  },
  {
    "step": "evaluate_model",
    "status": "fail",
    "timestamp": "2026-06-06T23:37:41",
    "roc_auc": 0.4883
  }
]